TOPSIS/102017047.py
TOPSIS/__init__.py
Topsis_Aadil_Singh_102017047-0.0.1.dist-info/LICENSE
Topsis_Aadil_Singh_102017047-0.0.1.dist-info/METADATA
Topsis_Aadil_Singh_102017047-0.0.1.dist-info/WHEEL
Topsis_Aadil_Singh_102017047-0.0.1.dist-info/top_level.txt
Topsis_Aadil_Singh_102017047-0.0.1.dist-info/RECORD
