Metadata-Version: 2.1
Name: Topsis-Aadil-Singh-102017047
Version: 0.0.1
Summary: Useful for solving MCDM problems
Home-page: https://github.com/pypa/sampleproject
Author: Aadil Singh
Author-email: aadilsandhu7@gmail.com
Project-URL: Bug Tracker, https://github.com/pypa/sampleproject/issues
Classifier: Programming Language :: Python :: 3
Classifier: License :: OSI Approved :: MIT License
Classifier: Operating System :: OS Independent
Requires-Python: >=3.6
License-File: LICENSE
